<?xml version="1.0"?>
<!DOCTYPE hibernate-mapping PUBLIC "-//Hibernate/Hibernate Mapping DTD 3.0//EN"
"http://www.hibernate.org/dtd/hibernate-mapping-3.0.dtd">
<!-- Generated Feb 2, 2016 9:54:14 AM by Hibernate Tools 3.6.0 -->
<hibernate-mapping>
    <class name="procuradoria.map.Uztfuncionario" table="UZTFUNCIONARIO" schema="ABPROCU">
        <id name="uztfuncionarioId" type="big_decimal">
            <column name="UZTFUNCIONARIO_ID" precision="22" scale="0" />
            <generator class="assigned" />
        </id>
        <property name="uztfuncionarioFlag" type="big_decimal">
            <column name="UZTFUNCIONARIO_FLAG" precision="22" scale="0" />
        </property>
        <property name="uztfuncionarioNombres" type="string">
            <column name="UZTFUNCIONARIO_NOMBRES" length="45" />
        </property>
        <property name="uztfuncionarioApellidos" type="string">
            <column name="UZTFUNCIONARIO_APELLIDOS" length="45" />
        </property>
        <property name="uztfuncionarioCedula" type="string">
            <column name="UZTFUNCIONARIO_CEDULA" length="15" />
        </property>
        <property name="uztfuncionarioEmail" type="string">
            <column name="UZTFUNCIONARIO_EMAIL" length="45" />
        </property>
        <property name="uztfuncionarioMovil" type="string">
            <column name="UZTFUNCIONARIO_MOVIL" length="15" />
        </property>
        <property name="uztfuncionarioIdbanner" type="string">
            <column name="UZTFUNCIONARIO_IDBANNER" length="25" />
        </property>
        <set name="uztrols" table="UZTROL" inverse="true" lazy="true" fetch="select">
            <key>
                <column name="UZTFUNCIONARIO_ID" precision="22" scale="0" not-null="true" />
            </key>
            <one-to-many class="procuradoria.map.Uztrol" />
        </set>
        <set name="uztasignars" table="UZTASIGNAR" inverse="true" lazy="true" fetch="select">
            <key>
                <column name="UZTFUNCIONARIO_ID" precision="22" scale="0" not-null="true" />
            </key>
            <one-to-many class="procuradoria.map.Uztasignar" />
        </set>
        <set name="uztinvolFfs" table="UZTINVOL_FF" inverse="true" lazy="true" fetch="select">
            <key>
                <column name="UZTFUNCIONARIO_ID" precision="22" scale="0" not-null="true" />
            </key>
            <one-to-many class="procuradoria.map.UztinvolFf" />
        </set>
    </class>
</hibernate-mapping>
